{
  "theme": "maple",
  "$schema": "https://mintlify.com/docs.json",
  "name": "Mintlify",
  "colors": {
    "primary": "#0D9373",
    "light": "#55D799",
    "dark": "#0D9373"
  },
  "logo": {
    "light": "/logo/light.svg",
    "dark": "/logo/dark.svg",
    "href": "https://mintlify.com"
  },
  "favicon": "/favicon.svg",
  "api": {
    "mdx": {
      "auth": {
        "method": "bearer"
      }
    }
  },
  "navbar": {
    "links": [
      {
        "label": "Community",
        "href": "https://mintlify.com/community"
      }
    ],
    "primary": {
      "type": "button",
      "label": "Get Started",
      "href": "https://mintlify.com/start"
    }
  },
  "navigation": {
    "languages": [
      {
        "language": "en",
        "dropdowns": [
          {
            "dropdown": "Documentation",
            "icon": "book",
            "description": "Set up your documentation",
            "groups": [
              {
                "group": "Getting Started",
                "pages": [
                  "index",
                  "quickstart",
                  "installation",
                  "editor",
                  "support"
                ]
              },
              {
                "group": "Core Configuration",
                "pages": [
                  "settings",
                  "pages",
                  "navigation",
                  "themes",
                  "settings/custom-domain",
                  "ai-ingestion"
                ]
              },
              {
                "group": "Components",
                "pages": [
                  "text",
                  "image-embeds",
                  "list-table",
                  "code",
                  "reusable-snippets",
                  "components/accordions",
                  "components/callouts",
                  "components/cards",
                  "components/columns",
                  "components/code-groups",
                  "components/examples",
                  "components/expandables",
                  "components/fields",
                  "components/frames",
                  "components/icons",
                  "components/mermaid-diagrams",
                  "components/panel",
                  "components/steps",
                  "components/tabs",
                  "components/tooltips",
                  "components/update"
                ]
              },
              {
                "group": "API Pages",
                "pages": [
                  "api-playground/overview",
                  {
                    "group": "OpenAPI",
                    "icon": "file-json",
                    "pages": [
                      "api-playground/openapi/setup",
                      "api-playground/openapi/writing-openapi",
                      "api-playground/openapi/advanced-features"
                    ]
                  },
                  {
                    "group": "AsyncAPI",
                    "icon": "webhook",
                    "pages": [
                      "api-playground/asyncapi/setup",
                      "api-playground/asyncapi/playground"
                    ]
                  },
                  {
                    "group": "MDX",
                    "icon": "markdown",
                    "pages": [
                      "api-playground/mdx/configuration",
                      "api-playground/mdx/authentication"
                    ]
                  },
                  "api-playground/troubleshooting"
                ]
              },
              {
                "group": "Authentication and Personalization",
                "pages": [
                  "settings/authentication-personalization/authentication",
                  "settings/authentication-personalization/partial-authentication",
                  "settings/authentication-personalization/personalization",
                  "settings/authentication-personalization/authentication-vs-personalization",
                  {
                    "group": "Authentication Setup",
                    "icon": "file-cog",
                    "pages": [
                      "settings/authentication-personalization/authentication-setup/choosing-a-handshake",
                      "settings/authentication-personalization/authentication-setup/password",
                      "settings/authentication-personalization/authentication-setup/jwt",
                      "settings/authentication-personalization/authentication-setup/oauth",
                      "settings/authentication-personalization/authentication-setup/mintlify"
                    ]
                  },
                  {
                    "group": "Personalization Setup",
                    "icon": "user-cog",
                    "pages": [
                      "settings/authentication-personalization/personalization-setup/choosing-a-handshake",
                      "settings/authentication-personalization/personalization-setup/shared-session",
                      "settings/authentication-personalization/personalization-setup/jwt",
                      "settings/authentication-personalization/personalization-setup/oauth"
                    ]
                  },
                  "settings/authentication-personalization/sending-data"
                ]
              },
              {
                "group": "Guides",
                "pages": [
                  "guides/migration",
                  "mcp",
                  "translations",
                  "guides/monorepo",
                  "react-components",
                  "settings/custom-scripts",
                  "settings/seo",
                  "guides/hidden-pages",
                  "settings/broken-links",
                  {
                    "group": "Custom Subdirectory",
                    "icon": "folder",
                    "pages": [
                      "advanced/subpath/cloudflare",
                      "advanced/subpath/route53-cloudfront",
                      "advanced/subpath/vercel"
                    ]
                  },
                  {
                    "group": "Dashboard Access",
                    "icon": "gauge",
                    "pages": [
                      "advanced/dashboard/sso",
                      "advanced/dashboard/permissions",
                      "advanced/dashboard/roles"
                    ]
                  }
                ]
              },
              {
                "group": "Integrations",
                "pages": [
                  {
                    "group": "Analytics",
                    "icon": "chart-no-axes-combined",
                    "pages": [
                      "integrations/analytics/overview",
                      "integrations/analytics/amplitude",
                      "integrations/analytics/clearbit",
                      "integrations/analytics/fathom",
                      "integrations/analytics/google-analytics",
                      "integrations/analytics/google-tag-manager",
                      "integrations/analytics/heap",
                      "integrations/analytics/hotjar",
                      "integrations/analytics/koala",
                      "integrations/analytics/logrocket",
                      "integrations/analytics/mixpanel",
                      "integrations/analytics/pirsch",
                      "integrations/analytics/plausible",
                      "integrations/analytics/posthog",
                      "integrations/analytics/segment"
                    ]
                  },
                  {
                    "group": "SDKs",
                    "icon": "folder-code",
                    "pages": [
                      "integrations/sdks/speakeasy",
                      "integrations/sdks/stainless"
                    ]
                  },
                  {
                    "group": "Support",
                    "icon": "messages-square",
                    "pages": [
                      "integrations/support/overview",
                      "integrations/support/intercom",
                      "integrations/support/front"
                    ]
                  },
                  {
                    "group": "Privacy",
                    "icon": "folder-lock",
                    "pages": [
                      "integrations/privacy/overview",
                      "integrations/privacy/osano"
                    ]
                  }
                ]
              },
              {
                "group": "Version Control and CI/CD",
                "pages": [
                  "settings/github",
                  "settings/gitlab",
                  "settings/ci",
                  "settings/preview-deployments"
                ]
              }
            ]
          },
          {
            "dropdown": "API Reference",
            "icon": "terminal",
            "description": "Reference for the API",
            "groups": [
              {
                "group": "API Reference",
                "pages": [
                  "api-reference/introduction"
                ]
              },
              {
                "group": "Admin",
                "pages": [
                  "api-reference/update/trigger",
                  "api-reference/update/status"
                ]
              },
              {
                "group": "Assistant",
                "pages": [
                  "api-reference/chat/create-topic",
                  "api-reference/chat/generate-message"
                ]
              }
            ]
          },
          {
            "dropdown": "Changelog",
            "icon": "history",
            "description": "Updates and changes",
            "groups": [
              {
                "group": "Changelog",
                "pages": [
                  "changelog"
                ]
              }
            ]
          }
        ]
      },
      {
        "dropdowns": [
          {
            "dropdown": "Dokumentasi",
            "icon": "book",
            "description": "Set up your documentation",
            "groups": [
              {
                "group": "Memulai",
                "pages": [
                  "id/index",
                  "id/quickstart",
                  "id/installation",
                  "id/editor",
                  "id/support"
                ]
              },
              {
                "group": "Konfigurasi Inti",
                "pages": [
                  "id/settings",
                  "id/pages",
                  "id/navigation",
                  "id/themes",
                  "id/settings/custom-domain",
                  "id/ai-ingestion"
                ]
              },
              {
                "group": "Komponen",
                "pages": [
                  "id/text",
                  "id/image-embeds",
                  "id/list-table",
                  "id/code",
                  "id/reusable-snippets",
                  "id/components/accordions",
                  "id/components/callouts",
                  "id/components/cards",
                  "id/components/columns",
                  "id/components/code-groups",
                  "id/components/examples",
                  "id/components/expandables",
                  "id/components/fields",
                  "id/components/frames",
                  "id/components/icons",
                  "id/components/mermaid-diagrams",
                  "id/components/panel",
                  "id/components/steps",
                  "id/components/tabs",
                  "id/components/tooltips",
                  "id/components/update"
                ]
              },
              {
                "group": "Halaman API",
                "pages": [
                  "id/api-playground/overview",
                  {
                    "group": "OpenAPI",
                    "icon": "file-json",
                    "pages": [
                      "id/api-playground/openapi/setup",
                      "id/api-playground/openapi/writing-openapi",
                      "id/api-playground/openapi/advanced-features"
                    ]
                  },
                  {
                    "group": "AsyncAPI",
                    "icon": "webhook",
                    "pages": [
                      "id/api-playground/asyncapi/setup",
                      "id/api-playground/asyncapi/playground"
                    ]
                  },
                  {
                    "group": "MDX",
                    "icon": "markdown",
                    "pages": [
                      "id/api-playground/mdx/configuration",
                      "id/api-playground/mdx/authentication"
                    ]
                  },
                  "id/api-playground/troubleshooting"
                ]
              },
              {
                "group": "Autentikasi dan Personalisasi",
                "pages": [
                  "id/settings/authentication-personalization/authentication",
                  "id/settings/authentication-personalization/partial-authentication",
                  "id/settings/authentication-personalization/personalization",
                  "id/settings/authentication-personalization/authentication-vs-personalization",
                  {
                    "group": "Pengaturan Autentikasi",
                    "icon": "file-cog",
                    "pages": [
                      "id/settings/authentication-personalization/authentication-setup/choosing-a-handshake",
                      "id/settings/authentication-personalization/authentication-setup/password",
                      "id/settings/authentication-personalization/authentication-setup/jwt",
                      "id/settings/authentication-personalization/authentication-setup/oauth",
                      "id/settings/authentication-personalization/authentication-setup/mintlify"
                    ]
                  },
                  {
                    "group": "Pengaturan Personalisasi",
                    "icon": "user-cog",
                    "pages": [
                      "id/settings/authentication-personalization/personalization-setup/choosing-a-handshake",
                      "id/settings/authentication-personalization/personalization-setup/shared-session",
                      "id/settings/authentication-personalization/personalization-setup/jwt",
                      "id/settings/authentication-personalization/personalization-setup/oauth"
                    ]
                  },
                  "id/settings/authentication-personalization/sending-data"
                ]
              },
              {
                "group": "Panduan",
                "pages": [
                  "id/guides/migration",
                  "id/mcp",
                  "id/translations",
                  "id/guides/monorepo",
                  "id/react-components",
                  "id/settings/custom-scripts",
                  "id/settings/seo",
                  "id/guides/hidden-pages",
                  "id/settings/broken-links",
                  {
                    "group": "Subdirektori Kustom",
                    "icon": "folder",
                    "pages": [
                      "id/advanced/subpath/cloudflare",
                      "id/advanced/subpath/route53-cloudfront",
                      "id/advanced/subpath/vercel"
                    ]
                  },
                  {
                    "group": "Akses Dashboard",
                    "icon": "gauge",
                    "pages": [
                      "id/advanced/dashboard/sso",
                      "id/advanced/dashboard/permissions",
                      "id/advanced/dashboard/roles"
                    ]
                  }
                ]
              },
              {
                "group": "Integrasi",
                "pages": [
                  {
                    "group": "Analitik",
                    "icon": "chart-no-axes-combined",
                    "pages": [
                      "id/integrations/analytics/overview",
                      "id/integrations/analytics/amplitude",
                      "id/integrations/analytics/clearbit",
                      "id/integrations/analytics/fathom",
                      "id/integrations/analytics/google-analytics",
                      "id/integrations/analytics/google-tag-manager",
                      "id/integrations/analytics/heap",
                      "id/integrations/analytics/hotjar",
                      "id/integrations/analytics/koala",
                      "id/integrations/analytics/logrocket",
                      "id/integrations/analytics/mixpanel",
                      "id/integrations/analytics/pirsch",
                      "id/integrations/analytics/plausible",
                      "id/integrations/analytics/posthog",
                      "id/integrations/analytics/segment"
                    ]
                  },
                  {
                    "group": "SDK",
                    "icon": "folder-code",
                    "pages": [
                      "id/integrations/sdks/speakeasy",
                      "id/integrations/sdks/stainless"
                    ]
                  },
                  {
                    "group": "Dukungan",
                    "icon": "messages-square",
                    "pages": [
                      "id/integrations/support/overview",
                      "id/integrations/support/intercom",
                      "id/integrations/support/front"
                    ]
                  },
                  {
                    "group": "Privasi",
                    "icon": "folder-lock",
                    "pages": [
                      "id/integrations/privacy/overview",
                      "id/integrations/privacy/osano"
                    ]
                  }
                ]
              },
              {
                "group": "Kontrol Versi dan CI/CD",
                "pages": [
                  "id/settings/github",
                  "id/settings/gitlab",
                  "id/settings/ci",
                  "id/settings/preview-deployments"
                ]
              }
            ]
          },
          {
            "dropdown": "Referensi API",
            "icon": "terminal",
            "description": "Reference for the API",
            "groups": [
              {
                "group": "Referensi API",
                "pages": [
                  "id/api-reference/introduction"
                ]
              },
              {
                "group": "Admin",
                "pages": [
                  "id/api-reference/update/trigger",
                  "id/api-reference/update/status"
                ]
              },
              {
                "group": "Asisten",
                "pages": [
                  "id/api-reference/chat/create-topic",
                  "id/api-reference/chat/generate-message"
                ]
              }
            ]
          },
          {
            "dropdown": "Changelog",
            "icon": "history",
            "description": "Updates and changes",
            "groups": [
              {
                "group": "Changelog",
                "pages": [
                  "id/changelog"
                ]
              }
            ]
          }
        ],
        "language": "id"
      },
      {
        "language": "pt-BR",
        "dropdowns": [
          {
            "dropdown": "Documentação",
            "icon": "book",
            "description": "Set up your documentation",
            "groups": [
              {
                "group": "Primeiros Passos",
                "pages": [
                  "pt-BR/index",
                  "pt-BR/quickstart",
                  "pt-BR/installation",
                  "pt-BR/editor",
                  "pt-BR/support"
                ]
              },
              {
                "group": "Configuração Principal",
                "pages": [
                  "pt-BR/settings",
                  "pt-BR/pages",
                  "pt-BR/navigation",
                  "pt-BR/themes",
                  "pt-BR/settings/custom-domain",
                  "pt-BR/ai-ingestion"
                ]
              },
              {
                "group": "Componentes",
                "pages": [
                  "pt-BR/text",
                  "pt-BR/image-embeds",
                  "pt-BR/list-table",
                  "pt-BR/code",
                  "pt-BR/reusable-snippets",
                  "pt-BR/components/accordions",
                  "pt-BR/components/callouts",
                  "pt-BR/components/cards",
                  "pt-BR/components/columns",
                  "pt-BR/components/code-groups",
                  "pt-BR/components/examples",
                  "pt-BR/components/expandables",
                  "pt-BR/components/fields",
                  "pt-BR/components/frames",
                  "pt-BR/components/icons",
                  "pt-BR/components/mermaid-diagrams",
                  "pt-BR/components/panel",
                  "pt-BR/components/steps",
                  "pt-BR/components/tabs",
                  "pt-BR/components/tooltips",
                  "pt-BR/components/update"
                ]
              },
              {
                "group": "Páginas de API",
                "pages": [
                  "pt-BR/api-playground/overview",
                  {
                    "group": "OpenAPI",
                    "icon": "file-json",
                    "pages": [
                      "pt-BR/api-playground/openapi/setup",
                      "pt-BR/api-playground/openapi/writing-openapi",
                      "pt-BR/api-playground/openapi/advanced-features"
                    ]
                  },
                  {
                    "group": "AsyncAPI",
                    "icon": "webhook",
                    "pages": [
                      "pt-BR/api-playground/asyncapi/setup",
                      "pt-BR/api-playground/asyncapi/playground"
                    ]
                  },
                  {
                    "group": "MDX",
                    "icon": "markdown",
                    "pages": [
                      "pt-BR/api-playground/mdx/configuration",
                      "pt-BR/api-playground/mdx/authentication"
                    ]
                  },
                  "pt-BR/api-playground/troubleshooting"
                ]
              },
              {
                "group": "Autenticação e Personalização",
                "pages": [
                  "pt-BR/settings/authentication-personalization/authentication",
                  "pt-BR/settings/authentication-personalization/partial-authentication",
                  "pt-BR/settings/authentication-personalization/personalization",
                  "pt-BR/settings/authentication-personalization/authentication-vs-personalization",
                  {
                    "group": "Configuração de Autenticação",
                    "icon": "file-cog",
                    "pages": [
                      "pt-BR/settings/authentication-personalization/authentication-setup/choosing-a-handshake",
                      "pt-BR/settings/authentication-personalization/authentication-setup/password",
                      "pt-BR/settings/authentication-personalization/authentication-setup/jwt",
                      "pt-BR/settings/authentication-personalization/authentication-setup/oauth",
                      "pt-BR/settings/authentication-personalization/authentication-setup/mintlify"
                    ]
                  },
                  {
                    "group": "Configuração de Personalização",
                    "icon": "user-cog",
                    "pages": [
                      "pt-BR/settings/authentication-personalization/personalization-setup/choosing-a-handshake",
                      "pt-BR/settings/authentication-personalization/personalization-setup/shared-session",
                      "pt-BR/settings/authentication-personalization/personalization-setup/jwt",
                      "pt-BR/settings/authentication-personalization/personalization-setup/oauth"
                    ]
                  },
                  "pt-BR/settings/authentication-personalization/sending-data"
                ]
              },
              {
                "group": "Guias",
                "pages": [
                  "pt-BR/guides/migration",
                  "pt-BR/mcp",
                  "pt-BR/translations",
                  "pt-BR/guides/monorepo",
                  "pt-BR/react-components",
                  "pt-BR/settings/custom-scripts",
                  "pt-BR/settings/seo",
                  "pt-BR/guides/hidden-pages",
                  "pt-BR/settings/broken-links",
                  {
                    "group": "Subdiretório Personalizado",
                    "icon": "folder",
                    "pages": [
                      "pt-BR/advanced/subpath/cloudflare",
                      "pt-BR/advanced/subpath/route53-cloudfront",
                      "pt-BR/advanced/subpath/vercel"
                    ]
                  },
                  {
                    "group": "Acesso ao Painel",
                    "icon": "gauge",
                    "pages": [
                      "pt-BR/advanced/dashboard/sso",
                      "pt-BR/advanced/dashboard/permissions",
                      "pt-BR/advanced/dashboard/roles"
                    ]
                  }
                ]
              },
              {
                "group": "Integrações",
                "pages": [
                  {
                    "group": "Análises",
                    "icon": "chart-no-axes-combined",
                    "pages": [
                      "pt-BR/integrations/analytics/overview",
                      "pt-BR/integrations/analytics/amplitude",
                      "pt-BR/integrations/analytics/clearbit",
                      "pt-BR/integrations/analytics/fathom",
                      "pt-BR/integrations/analytics/google-analytics",
                      "pt-BR/integrations/analytics/google-tag-manager",
                      "pt-BR/integrations/analytics/heap",
                      "pt-BR/integrations/analytics/hotjar",
                      "pt-BR/integrations/analytics/koala",
                      "pt-BR/integrations/analytics/logrocket",
                      "pt-BR/integrations/analytics/mixpanel",
                      "pt-BR/integrations/analytics/pirsch",
                      "pt-BR/integrations/analytics/plausible",
                      "pt-BR/integrations/analytics/posthog",
                      "pt-BR/integrations/analytics/segment"
                    ]
                  },
                  {
                    "group": "SDKs",
                    "icon": "folder-code",
                    "pages": [
                      "pt-BR/integrations/sdks/speakeasy",
                      "pt-BR/integrations/sdks/stainless"
                    ]
                  },
                  {
                    "group": "Suporte",
                    "icon": "messages-square",
                    "pages": [
                      "pt-BR/integrations/support/overview",
                      "pt-BR/integrations/support/intercom",
                      "pt-BR/integrations/support/front"
                    ]
                  },
                  {
                    "group": "Privacidade",
                    "icon": "folder-lock",
                    "pages": [
                      "pt-BR/integrations/privacy/overview",
                      "pt-BR/integrations/privacy/osano"
                    ]
                  }
                ]
              },
              {
                "group": "Controle de Versão e CI/CD",
                "pages": [
                  "pt-BR/settings/github",
                  "pt-BR/settings/gitlab",
                  "pt-BR/settings/ci",
                  "pt-BR/settings/preview-deployments"
                ]
              }
            ]
          },
          {
            "dropdown": "Referência da API",
            "icon": "terminal",
            "description": "Reference for the API",
            "groups": [
              {
                "group": "Referência da API",
                "pages": [
                  "pt-BR/api-reference/introduction"
                ]
              },
              {
                "group": "Admin",
                "pages": [
                  "pt-BR/api-reference/update/trigger",
                  "pt-BR/api-reference/update/status"
                ]
              },
              {
                "group": "Assistente",
                "pages": [
                  "pt-BR/api-reference/chat/create-topic",
                  "pt-BR/api-reference/chat/generate-message"
                ]
              }
            ]
          },
          {
            "dropdown": "Registro de Alterações",
            "icon": "history",
            "description": "Updates and changes",
            "groups": [
              {
                "group": "Registro de Alterações",
                "pages": [
                  "pt-BR/changelog"
                ]
              }
            ]
          }
        ]
      },
      {
        "language": "es",
        "dropdowns": [
          {
            "dropdown": "Documentación",
            "icon": "book",
            "description": "Set up your documentation",
            "groups": [
              {
                "group": "Primeros pasos",
                "pages": [
                  "es/index",
                  "es/quickstart",
                  "es/installation",
                  "es/editor",
                  "es/support"
                ]
              },
              {
                "group": "Configuración principal",
                "pages": [
                  "es/settings",
                  "es/pages",
                  "es/navigation",
                  "es/themes",
                  "es/settings/custom-domain",
                  "es/ai-ingestion"
                ]
              },
              {
                "group": "Componentes",
                "pages": [
                  "es/text",
                  "es/image-embeds",
                  "es/list-table",
                  "es/code",
                  "es/reusable-snippets",
                  "es/components/accordions",
                  "es/components/callouts",
                  "es/components/cards",
                  "es/components/columns",
                  "es/components/code-groups",
                  "es/components/examples",
                  "es/components/expandables",
                  "es/components/fields",
                  "es/components/frames",
                  "es/components/icons",
                  "es/components/mermaid-diagrams",
                  "es/components/panel",
                  "es/components/steps",
                  "es/components/tabs",
                  "es/components/tooltips",
                  "es/components/update"
                ]
              },
              {
                "group": "Páginas de API",
                "pages": [
                  "es/api-playground/overview",
                  {
                    "group": "OpenAPI",
                    "icon": "file-json",
                    "pages": [
                      "es/api-playground/openapi/setup",
                      "es/api-playground/openapi/writing-openapi",
                      "es/api-playground/openapi/advanced-features"
                    ]
                  },
                  {
                    "group": "AsyncAPI",
                    "icon": "webhook",
                    "pages": [
                      "es/api-playground/asyncapi/setup",
                      "es/api-playground/asyncapi/playground"
                    ]
                  },
                  {
                    "group": "MDX",
                    "icon": "markdown",
                    "pages": [
                      "es/api-playground/mdx/configuration",
                      "es/api-playground/mdx/authentication"
                    ]
                  },
                  "es/api-playground/troubleshooting"
                ]
              },
              {
                "group": "Autenticación y Personalización",
                "pages": [
                  "es/settings/authentication-personalization/authentication",
                  "es/settings/authentication-personalization/partial-authentication",
                  "es/settings/authentication-personalization/personalization",
                  "es/settings/authentication-personalization/authentication-vs-personalization",
                  {
                    "group": "Configuración de autenticación",
                    "icon": "file-cog",
                    "pages": [
                      "es/settings/authentication-personalization/authentication-setup/choosing-a-handshake",
                      "es/settings/authentication-personalization/authentication-setup/password",
                      "es/settings/authentication-personalization/authentication-setup/jwt",
                      "es/settings/authentication-personalization/authentication-setup/oauth",
                      "es/settings/authentication-personalization/authentication-setup/mintlify"
                    ]
                  },
                  {
                    "group": "Configuración de personalización",
                    "icon": "user-cog",
                    "pages": [
                      "es/settings/authentication-personalization/personalization-setup/choosing-a-handshake",
                      "es/settings/authentication-personalization/personalization-setup/shared-session",
                      "es/settings/authentication-personalization/personalization-setup/jwt",
                      "es/settings/authentication-personalization/personalization-setup/oauth"
                    ]
                  },
                  "es/settings/authentication-personalization/sending-data"
                ]
              },
              {
                "group": "Guías",
                "pages": [
                  "es/guides/migration",
                  "es/mcp",
                  "es/translations",
                  "es/guides/monorepo",
                  "es/react-components",
                  "es/settings/custom-scripts",
                  "es/settings/seo",
                  "es/guides/hidden-pages",
                  "es/settings/broken-links",
                  {
                    "group": "Subdirectorio personalizado",
                    "icon": "folder",
                    "pages": [
                      "es/advanced/subpath/cloudflare",
                      "es/advanced/subpath/route53-cloudfront",
                      "es/advanced/subpath/vercel"
                    ]
                  },
                  {
                    "group": "Acceso al panel",
                    "icon": "gauge",
                    "pages": [
                      "es/advanced/dashboard/sso",
                      "es/advanced/dashboard/permissions",
                      "es/advanced/dashboard/roles"
                    ]
                  }
                ]
              },
              {
                "group": "Integraciones",
                "pages": [
                  {
                    "group": "Analíticas",
                    "icon": "chart-no-axes-combined",
                    "pages": [
                      "es/integrations/analytics/overview",
                      "es/integrations/analytics/amplitude",
                      "es/integrations/analytics/clearbit",
                      "es/integrations/analytics/fathom",
                      "es/integrations/analytics/google-analytics",
                      "es/integrations/analytics/google-tag-manager",
                      "es/integrations/analytics/heap",
                      "es/integrations/analytics/hotjar",
                      "es/integrations/analytics/koala",
                      "es/integrations/analytics/logrocket",
                      "es/integrations/analytics/mixpanel",
                      "es/integrations/analytics/pirsch",
                      "es/integrations/analytics/plausible",
                      "es/integrations/analytics/posthog",
                      "es/integrations/analytics/segment"
                    ]
                  },
                  {
                    "group": "SDKs",
                    "icon": "folder-code",
                    "pages": [
                      "es/integrations/sdks/speakeasy",
                      "es/integrations/sdks/stainless"
                    ]
                  },
                  {
                    "group": "Soporte",
                    "icon": "messages-square",
                    "pages": [
                      "es/integrations/support/overview",
                      "es/integrations/support/intercom",
                      "es/integrations/support/front"
                    ]
                  },
                  {
                    "group": "Privacidad",
                    "icon": "folder-lock",
                    "pages": [
                      "es/integrations/privacy/overview",
                      "es/integrations/privacy/osano"
                    ]
                  }
                ]
              },
              {
                "group": "Control de versiones y CI/CD",
                "pages": [
                  "es/settings/github",
                  "es/settings/gitlab",
                  "es/settings/ci",
                  "es/settings/preview-deployments"
                ]
              }
            ]
          },
          {
            "dropdown": "Referencia de API",
            "icon": "terminal",
            "description": "Reference for the API",
            "groups": [
              {
                "group": "Referencia de API",
                "pages": [
                  "es/api-reference/introduction"
                ]
              },
              {
                "group": "Admin",
                "pages": [
                  "es/api-reference/update/trigger",
                  "es/api-reference/update/status"
                ]
              },
              {
                "group": "Asistente",
                "pages": [
                  "es/api-reference/chat/create-topic",
                  "es/api-reference/chat/generate-message"
                ]
              }
            ]
          },
          {
            "dropdown": "Registro de cambios",
            "icon": "history",
            "description": "Updates and changes",
            "groups": [
              {
                "group": "Registro de cambios",
                "pages": [
                  "es/changelog"
                ]
              }
            ]
          }
        ]
      }
    ]
  },
  "footer": {
    "socials": {
      "x": "https://x.com/mintlify",
      "linkedin": "https://www.linkedin.com/company/mintlify",
      "github": "https://github.com/mintlify",
      "slack": "https://mintlify.com/community"
    },
    "links": [
      {
        "header": "Resources",
        "items": [
          {
            "label": "Customers",
            "href": "https://mintlify.com/customers"
          },
          {
            "label": "Enterprise",
            "href": "https://mintlify.com/enterprise"
          },
          {
            "label": "Request Preview",
            "href": "https://mintlify.com/preview"
          },
          {
            "label": "Integrations",
            "href": "https://mintlify.com/docs/integrations/analytics/overview"
          },
          {
            "label": "Templates",
            "href": "https://mintlify.com/docs/themes"
          },
          {
            "label": "Wall of Love",
            "href": "https://mintlify.com/love"
          }
        ]
      },
      {
        "header": "Company",
        "items": [
          {
            "label": "Careers",
            "href": "https://mintlify.com/careers"
          },
          {
            "label": "Blog",
            "href": "https://mintlify.com/blog"
          },
          {
            "label": "Feature Requests",
            "href": "https://github.com/orgs/mintlify/discussions/categories/feature-requests"
          },
          {
            "label": "Security",
            "href": "https://mintlify.com/security/responsible-disclosure"
          }
        ]
      },
      {
        "header": "Legal",
        "items": [
          {
            "label": "Privacy Policy",
            "href": "https://mintlify.com/legal/privacy"
          },
          {
            "label": "Terms of Service",
            "href": "https://mintlify.com/legal/terms"
          }
        ]
      }
    ]
  },
  "icons": {
    "library": "lucide"
  },
  "integrations": {
    "ga4": {
      "measurementId": "G-RCYWHL7EQ7"
    },
    "koala": {
      "publicApiKey": "pk_76a6caa274e800f3ceff0b2bc6b9b9d82ab8"
    }
  },
  "contextual": {
    "options": [
      "copy",
      "view",
      "chatgpt",
      "claude"
    ]
  }
}